<recipe>
  <name>Cinnamon Cake Rolls</name>
  <safe_name></safe_name>
  <primary_category>Breakfast</primary_category>
  <untried></untried>
  <secondary_categories>
    <secondary_category>Bill's Favorite</secondary_category>
  </secondary_categories>
  <yield_count>12</yield_count>
  <yield_measure>large rolls</yield_measure>
  <prep_time></prep_time>
  <notes>It seemed that for a time puddingless yellow cake was a difficult find.  In 2016 you can find it as a "classic" like the soups that water once staples and are now relegated to a survival role as a seasoning.

These rolls expand up rather obscenely large.</notes>
  <ingredients>
    <ingredient>
      <quantity>1 (18.5 oz)</quantity>
      <ingredient_name>package classic yellow cake mix</ingredient_name>
      <preparation>non "moist"</preparation>
    </ingredient>
    <ingredient>
      <quantity>2 1/4 tsp</quantity>
      <ingredient_name>dry yeast</ingredient_name>
      <preparation></preparation>
    </ingredient>
    <ingredient>
      <quantity>5 cups</quantity>
      <ingredient_name>all-purpose flour</ingredient_name>
      <preparation></preparation>
    </ingredient>
    <ingredient>
      <quantity>2 1/2 cups</quantity>
      <ingredient_name>water</ingredient_name>
      <preparation>warmed to less than 120F</preparation>
    </ingredient>
    <ingredient>
      <quantity>1 stick</quantity>
      <ingredient_name>butter</ingredient_name>
      <preparation>softened</preparation>
    </ingredient>
    <ingredient>
      <quantity></quantity>
      <ingredient_name>sugar</ingredient_name>
      <preparation></preparation>
    </ingredient>
    <ingredient>
      <quantity></quantity>
      <ingredient_name>cinnamon</ingredient_name>
      <preparation></preparation>
    </ingredient>
    <ingredient>
      <quantity></quantity>
      <ingredient_name>**TOPPING</ingredient_name>
      <preparation></preparation>
    </ingredient>
    <ingredient>
      <quantity>1/4 cup</quantity>
      <ingredient_name>butter</ingredient_name>
      <preparation>melted</preparation>
    </ingredient>
    <ingredient>
      <quantity>1/2 cup</quantity>
      <ingredient_name>packed brown sugar</ingredient_name>
      <preparation></preparation>
    </ingredient>
    <ingredient>
      <quantity>1/2 cup</quantity>
      <ingredient_name>chopped pecans</ingredient_name>
      <preparation></preparation>
    </ingredient>
  </ingredients>
  <preparation>Combine cake mix, yeast and flour before mixing in water..  A machine would be best as the dough should be electric  Cover mixture with moist towel and let double, about thirty minutes in a warm environment

Turn out onto a lightly floured surface and roll out into a 10x16 rectangle.  Spread with softened butter.  Sprinkle with sugar and cinnamon.

Roll length-wise in the longest direction with the coating on the inside like you would if anyone still made jelly rolls.  Slice rolls in 2" intervals.  Arrange in buttered pans and cover to double again.  

Prepare topping by cooking ingredients until butter has melted and pour over rolls immediately before baking at 375F for 25 minutes.

Turn out onto serving plate immediately after removing from oven.</preparation>
  <source_author></source_author>
  <source_name>"Almanor Westshore Cooks", Contributed by Polly Justason, mother of Gary Kluge</source_name>
  <source_page>162</source_page>
  <source_date>1992</source_date>
  <entry_app>EH 3.0</entry_app>
  <cdate></cdate>
  <mdate>2016-05-14</mdate>
  <user>billp</user>
</recipe>
