<recipe>
  <source_page></source_page>
  <safe_name>Gums_Berry_And_Apple_Pie</safe_name>
  <primary_category>Desserts</primary_category>
  <preparation>Pare, slice and cook apples in near-boiling water until soft but not mashed--about 10 mins.

Mix flour and salt and cut in ice water slowly to form crust.  Roll out to form a 10-12" inch disk, large enough to cover a 9" casserole and chill.  

Drain apples and mix with boysenberries and sugar until evenly mixed.  Cover with with the dough disc and bake 35 to 45 minutes: 10 minutes at 450F for 10 minutes then step down to 350F.</preparation>
  <yield_count></yield_count>
  <yield_measure>Servings</yield_measure>
  <cdate></cdate>
  <prep_time></prep_time>
  <name>Gum's Berry And Apple Pie</name>
  <secondary_categories>
    <secondary_categorie>Bill's Favorite</secondary_categorie>
  </secondary_categories>
  <source_date></source_date>
  <source_name></source_name>
  <notes>Gum always made this for us when we'd come visiting.  She used a ceramic blackbird poking through the center  of the crust to  keep it from collapsing in on itself overly much and to work as a vent.  The little bastards are  hard to find, but well worth the  effort -- the pie wouldn't look the same without the little head peeping out. 

This being said, my crust generally falls in but its still tasty.</notes>
  <ingredients>
    <ingredient>
      <ingredient_name>flour</ingredient_name>
      <quantity>2 1/2 cups</quantity>
      <preparation/>
    </ingredient>
    <ingredient>
      <ingredient_name>salt</ingredient_name>
      <quantity>1/2 tsp</quantity>
      <preparation/>
    </ingredient>
    <ingredient>
      <ingredient_name>ice water</ingredient_name>
      <quantity>2/3 cup</quantity>
      <preparation/>
    </ingredient>
    <ingredient>
      <ingredient_name>apples</ingredient_name>
      <quantity>2-4</quantity>
      <preparation/>
    </ingredient>
    <ingredient>
      <ingredient_name>boysenberries</ingredient_name>
      <quantity>1 bag</quantity>
      <preparation/>
    </ingredient>
    <ingredient>
      <ingredient_name>sugar</ingredient_name>
      <quantity>1 1/4 cup</quantity>
      <preparation/>
    </ingredient>
  </ingredients>
  <mdate></mdate>
</recipe>
